pyjuggler/__init__.py
pyjuggler/juggler.py
pyjuggler-0.1.0.dist-info/LICENSE
pyjuggler-0.1.0.dist-info/WHEEL
pyjuggler-0.1.0.dist-info/METADATA
pyjuggler-0.1.0.dist-info/RECORD
